flexibuff/__init__.py
flexibuff-0.3.1.dist-info/METADATA
flexibuff-0.3.1.dist-info/WHEEL
flexibuff-0.3.1.dist-info/licenses/LICENSE
flexibuff-0.3.1.dist-info/RECORD
