Metadata-Version: 2.4
Name: flexibuff
Version: 0.3.1
Summary: Multi-Agent RL memory buffer which supports Numpy array and PyTorch Tensor formats
Project-URL: Homepage, https://github.com/Timothy-Flavin/flexibuff/
Project-URL: Bug Tracker, https://github.com/Timothy-Flavin/flexibuff/issues
Author-email: Timothy Flavin <timothy.c.flavin@gmail.com>
License-File: LICENSE
Classifier: License :: OSI Approved :: GNU General Public License v2 (GPLv2)
Classifier: Operating System :: OS Independent
Classifier: Programming Language :: Python :: 3
Requires-Python: >=3.7
